{"id":3375,"name":"涼宮ハルヒの消失","name_cn":"凉宫春日的消失","type":"动画","image":"9b/9b/3375_7lgL4.jpg","link":"https://bgm.tv/subject/3375","eps":1,"collection":{"on_hold":463,"dropped":122,"wish":3669,"collect":22794,"doing":384},"date":"2010-02-06","summary":"转眼间经已12月18日，凉宫春日期待已久的圣诞节即将来临。SOS团火锅派对的活动拍板以后，阿虚就带着烦恼回家。第二天，阿虚如常上学，但他很快注意到，学校发生了与平日完全不同的事。应该在后面的座位的凉宫春日不在，却换上了理应让长门有希消灭了的朝仓凉子……","rating":{"rank":20,"total":15954,"count":{"1":34,"2":8,"3":11,"4":26,"5":101,"6":377,"7":1365,"8":4116,"9":5779,"10":4137},"score":8.7},"updated_at":"2023-10-25T20:51:40+08:00"}