{"id":37154,"name":"ココロコネクト","name_cn":"心灵链环","type":"动画","image":"07/2e/37154_69Axl.jpg","link":"https://bgm.tv/subject/37154","eps":17,"collection":{"on_hold":574,"dropped":330,"wish":1823,"collect":7286,"doing":694},"date":"2012-07-07","summary":"本作的舞台位于私立山星高中，在这所学校的文化研究部内，八重樫太一、永濑伊织、稻叶姬子、桐山唯、青木义文这五名成员目前面临着不可思议的现象。起初是成员中的唯及义文，在毫无前兆的情况下发生了人格交换，之后周围的其他成员也是如此。爱与青春的五角形喜剧从此正式开演了。","rating":{"rank":1072,"total":5402,"count":{"1":16,"2":7,"3":10,"4":56,"5":147,"6":675,"7":1747,"8":2074,"9":508,"10":162},"score":7.4},"updated_at":"2023-10-26T05:37:51+08:00"}